aadharverify/__init__.py
aadharverify/module.py
tests/__init__.py
tests/test_module.py
aadharverify-0.1.dist-info/LICENCE
aadharverify-0.1.dist-info/METADATA
aadharverify-0.1.dist-info/WHEEL
aadharverify-0.1.dist-info/top_level.txt
aadharverify-0.1.dist-info/RECORD
